flow/__init__.py
flow/dataset.py
flow/distribute.py
flow/flow_main.py
flow/learner.py
flow/model.py
flow/numpy_encoder.py
flow/utils.py
flow/callbacks/__init__.py
flow/callbacks/checkpointer.py
flow/callbacks/early_stop.py
flow/callbacks/history.py
flow/callbacks/reduce_lr_on_plateau.py
flow/callbacks/timers.py
flow/config/__init__.py
flow/config/config.py
flow/distributed/__init__.py
flow/distributed/distributed_dataset.py
flow/distributed/distributed_learner.py
flow/distributed/distributed_model.py
flow/distributed/distributed_strategy_manager.py
flow/layers/__init__.py
flow/layers/flow_layer.py
learn_flow-0.1.25.dist-info/METADATA
learn_flow-0.1.25.dist-info/WHEEL
learn_flow-0.1.25.dist-info/top_level.txt
learn_flow-0.1.25.dist-info/RECORD
