Metadata-Version: 2.1
Name: learn-flow
Version: 0.1.25
Summary: An Structural framework to create machine learning models using tensorflow.
Home-page: UNKNOWN
Author: Luis Felipe Muller
Author-email: luisfmuller@gmail.com
License: UNKNOWN
Platform: UNKNOWN
Requires-Dist: absl-py (>=0.7.0)
Requires-Dist: astor (>=0.7.1)
Requires-Dist: blinker (==1.4)
Requires-Dist: gast (==0.2.2)
Requires-Dist: grpcio (>=1.18.0)
Requires-Dist: h5py (>=2.9.0)
Requires-Dist: markdown (>=3.0.1)
Requires-Dist: numpy (>=1.16.0)
Requires-Dist: protobuf (>=3.6.1)
Requires-Dist: six (>=1.12.0)
Requires-Dist: termcolor (==1.1.0)
Requires-Dist: werkzeug (>=0.14.1)
Requires-Dist: wheel (>=0.32.3) ; python_version >= "3"
